{
"type": "FeatureCollection",
"crs": { "type": "name", "properties": { "name": "urn:ogc:def:crs:OGC:1.3:CRS84" } },
"features": [
{ "type": "Feature", "properties": { "longitude": 69.17097, "latitude": 34.523971, "number": 8, "facility_number": "118", "facility_name": "Central Clinic of Police Commandant Kabul", "facility_type": "Health Facilities", "province": "Kabul", "district": "Kabul", "parent_pd": 0, "village": 0, "max_people": 0, "people": "Rent", "admin_staff": null, "land_ownership": null }, "geometry": { "type": "Point", "coordinates": [ 69.17097, 34.523971 ] } },
{ "type": "Feature", "properties": { "longitude": 69.11432, "latitude": 34.53732, "number": 104, "facility_number": "222", "facility_name": "Rehabilitation of Kitchen, Central hospital for out of bend patients, ", "facility_type": "Health Facilities", "province": "Kabul", "district": "Kabul City", "parent_pd": 0, "village": 0, "max_people": 0, "people": "Rent", "admin_staff": null, "land_ownership": null }, "geometry": { "type": "Point", "coordinates": [ 69.11432, 34.53732 ] } },
{ "type": "Feature", "properties": { "longitude": 69.11432, "latitude": 34.53732, "number": 105, "facility_number": "223", "facility_name": "Rehabilitation of police academy health clinic, Kabul", "facility_type": "Health Facilities", "province": "Kabul", "district": "Kabul City", "parent_pd": 0, "village": 0, "max_people": 0, "people": "Rent", "admin_staff": null, "land_ownership": null }, "geometry": { "type": "Point", "coordinates": [ 69.11432, 34.53732 ] } },
{ "type": "Feature", "properties": { "longitude": 69.11432, "latitude": 34.53732, "number": 111, "facility_number": "231", "facility_name": "Office for general surgery, Health clinic Kabul", "facility_type": "Health Facilities", "province": "Kabul", "district": "Kabul City", "parent_pd": 0, "village": 0, "max_people": 0, "people": "Rent", "admin_staff": null, "land_ownership": null }, "geometry": { "type": "Point", "coordinates": [ 69.11432, 34.53732 ] } },
{ "type": "Feature", "properties": { "longitude": 69.114, "latitude": 34.48, "number": 112, "facility_number": "232", "facility_name": "Health store for national police, Kabul", "facility_type": "Health Facilities", "province": "Kabul", "district": "Kabul City", "parent_pd": 0, "village": 0, "max_people": 0, "people": "Rent", "admin_staff": null, "land_ownership": null }, "geometry": { "type": "Point", "coordinates": [ 69.114, 34.48 ] } },
{ "type": "Feature", "properties": { "longitude": 69.11718, "latitude": 34.53798, "number": 127, "facility_number": "248", "facility_name": "Health commandant for national police, PD5", "facility_type": "Health Facilities", "province": "Kabul", "district": "PD5", "parent_pd": 0, "village": 0, "max_people": 0, "people": "Gov.", "admin_staff": null, "land_ownership": null }, "geometry": { "type": "Point", "coordinates": [ 69.11718, 34.53798 ] } }
]
}
